integration/__init__.py
integration/busybox.py
integration/test_client.py
integration/test_cluster_members.py
integration/test_containers.py
integration/test_images.py
integration/test_networks.py
integration/test_profiles.py
integration/test_projects.py
integration/test_storage.py
integration/testing.py
migration/__init__.py
migration/busybox.py
migration/test_containers.py
migration/testing.py
pylxd/__init__.py
pylxd/client.py
pylxd/exceptions.py
pylxd/managers.py
pylxd/models/__init__.py
pylxd/models/_model.py
pylxd/models/certificate.py
pylxd/models/cluster.py
pylxd/models/container.py
pylxd/models/image.py
pylxd/models/instance.py
pylxd/models/network.py
pylxd/models/operation.py
pylxd/models/profile.py
pylxd/models/project.py
pylxd/models/storage_pool.py
pylxd/models/virtual_machine.py
pylxd/models/tests/__init__.py
pylxd/models/tests/test_certificate.py
pylxd/models/tests/test_cluster.py
pylxd/models/tests/test_cluster_certificate.py
pylxd/models/tests/test_cluster_member.py
pylxd/models/tests/test_image.py
pylxd/models/tests/test_instance.py
pylxd/models/tests/test_model.py
pylxd/models/tests/test_network.py
pylxd/models/tests/test_operation.py
pylxd/models/tests/test_profile.py
pylxd/models/tests/test_project.py
pylxd/models/tests/test_storage.py
pylxd/tests/__init__.py
pylxd/tests/mock_lxd.py
pylxd/tests/test_client.py
pylxd/tests/testing.py
pylxd-2.3.5.dist-info/LICENSE
pylxd-2.3.5.dist-info/METADATA
pylxd-2.3.5.dist-info/WHEEL
pylxd-2.3.5.dist-info/top_level.txt
pylxd-2.3.5.dist-info/RECORD
