Metadata-Version: 2.1
Name: pylxd
Version: 2.3.5
Summary: python library for LXD
Home-page: https://ubuntu.com/lxd
Author: Paul Hummer and others (see CONTRIBUTORS.rst)
Author-email: lxd@lists.canonical.com
Classifier: Intended Audience :: Information Technology
Classifier: Intended Audience :: System Administrators
Classifier: License :: OSI Approved :: Apache Software License
Classifier: Operating System :: POSIX :: Linux
Classifier: Programming Language :: Python :: 3
Requires-Python: >=3.8
License-File: LICENSE
Requires-Dist: cryptography>=3.2
Requires-Dist: python-dateutil>=2.4.2
Requires-Dist: requests>=2.20.0
Requires-Dist: requests-toolbelt>=0.8.0
Requires-Dist: ws4py!=0.3.5,>=0.3.4
Provides-Extra: testing
Requires-Dist: ddt>=0.7.0; extra == "testing"
Requires-Dist: mock-services>=0.3; extra == "testing"
Requires-Dist: pytest-cov==2.10.1; extra == "testing"
Requires-Dist: pytest>=6.1.2; extra == "testing"
Requires-Dist: requests-mock<1.2; extra == "testing"
Requires-Dist: setuptools; extra == "testing"
Provides-Extra: format
Requires-Dist: black==23.1.0; extra == "format"
Requires-Dist: flake8>=2.5.0; extra == "format"
Requires-Dist: isort==5.6.4; extra == "format"
Provides-Extra: check
Requires-Dist: mypy; extra == "check"
Provides-Extra: doc
Requires-Dist: Sphinx; extra == "doc"
